AbstractSerializer/__init__.py
AbstractSerializer/abstract_serializer.py
AbstractSerializer/constants.py
ConcreteSerializer/__init__.py
ConcreteSerializer/constants.py
ConcreteSerializer/serializer.py
Parser/__init__.py
Parser/parser.py
Parser/json/__init__.py
Parser/json/constants.py
Parser/json/json.py
Parser/json/json_parser.py
Parser/xml/__init__.py
Parser/xml/constants.py
Parser/xml/xml.py
Parser/xml/xml_parser.py
lr3_Serializer-1.0.0.dist-info/LICENCE.txt
lr3_Serializer-1.0.0.dist-info/METADATA
lr3_Serializer-1.0.0.dist-info/WHEEL
lr3_Serializer-1.0.0.dist-info/top_level.txt
lr3_Serializer-1.0.0.dist-info/RECORD
