Metadata-Version: 2.1
Name: lr3-Serializer
Version: 1.0.0
Summary: Serialization library
Home-page: https://github.com/StrawberryAttacks/IGI
Author: StrawberryAttacks
Author-email: flufflepuffxx@gmail.com
License: MIT
Platform: UNKNOWN
Classifier: Intended Audience :: Developers
Classifier: License :: OSI Approved :: MIT License
Classifier: Programming Language :: Python
Classifier: Programming Language :: Python :: 3.10
Classifier: Operating System :: OS Independent
License-File: LICENCE.txt
